example_server/__init__.py
example_server/main.py
mcp_example_server-0.1.3.dist-info/METADATA
mcp_example_server-0.1.3.dist-info/WHEEL
mcp_example_server-0.1.3.dist-info/entry_points.txt
mcp_example_server-0.1.3.dist-info/RECORD
