Metadata-Version: 2.4
Name: mcp-example-server
Version: 0.1.3
Summary: Servidor MCP de exemplo (echo e time_now)
Author: TCC Lab
Keywords: example,mcp,model-context-protocol
Classifier: Operating System :: OS Independent
Classifier: Programming Language :: Python :: 3
Classifier: Programming Language :: Python :: 3 :: Only
Classifier: Programming Language :: Python :: 3.10
Requires-Python: >=3.10
Requires-Dist: mcp[cli]>=1.13.0
Provides-Extra: dev
Requires-Dist: black>=24.0; extra == 'dev'
Requires-Dist: pytest>=7.0; extra == 'dev'
Requires-Dist: ruff>=0.4.0; extra == 'dev'
